CHANGES.txt
LICENSE.txt
MANIFEST.in
README.txt
distribute_setup.py
setup.cfg
setup.py
CMCpy.egg-info/PKG-INFO
CMCpy.egg-info/SOURCES.txt
CMCpy.egg-info/dependency_links.txt
CMCpy.egg-info/entry_points.txt
CMCpy.egg-info/requires.txt
CMCpy.egg-info/top_level.txt
bin/cmc
cmcpy/__init__.py
cmcpy/__main__.py
cmcpy/amino_acid_spaces.py
cmcpy/codon_spaces.py
cmcpy/evolvers.py
cmcpy/genetic_codes.py
cmcpy/misreading.py
cmcpy/observables.py
cmcpy/site_type_spaces.py
doc/CMCpy.info
doc/CMCpy.pdf
doc/html/.buildinfo
doc/html/cmcpy.html
doc/html/genindex.html
doc/html/index.rtf
doc/html/objects.inv
doc/html/py-modindex.html
doc/html/search.html
doc/html/searchindex.js
doc/html/_modules/amino_acid_spaces.html
doc/html/_modules/codon_spaces.html
doc/html/_modules/evolvers.html
doc/html/_modules/genetic_codes.html
doc/html/_modules/index.html
doc/html/_modules/misreading.html
doc/html/_modules/observables.html
doc/html/_modules/site_type_spaces.html
doc/html/_sources/cmcpy.txt
doc/html/_sources/index.txt
doc/html/_static/ajax-loader.gif
doc/html/_static/basic.css
doc/html/_static/comment-bright.png
doc/html/_static/comment-close.png
doc/html/_static/comment.png
doc/html/_static/default.css
doc/html/_static/doctools.js
doc/html/_static/down-pressed.png
doc/html/_static/down.png
doc/html/_static/file.png
doc/html/_static/jquery.js
doc/html/_static/minus.png
doc/html/_static/plus.png
doc/html/_static/pygments.css
doc/html/_static/searchtools.js
doc/html/_static/sidebar.js
doc/html/_static/underscore.js
doc/html/_static/up-pressed.png
doc/html/_static/up.png
doc/html/_static/websupport.js