Metadata-Version: 1.0
Name: CMCpy
Version: 0.3
Summary: Genetic Code-Message Coevolution in Python
Home-page: http://pypi.python.org/pypi/CMCpy/
Author: David H. Ardell
Author-email: dardell@ucmerced.edu
License: Apache 2.0
Platform: UNKNOWN
